LICENSE
MANIFEST.in
README.md
requirements.txt
setup.py
regtricks/__init__.py
regtricks/_version.py
regtricks/application_helpers.py
regtricks/fnirt_coefficients.py
regtricks/image_space.py
regtricks/multiplication.py
regtricks/wrappers.py
regtricks/x5_interface.py
regtricks.egg-info/PKG-INFO
regtricks.egg-info/SOURCES.txt
regtricks.egg-info/dependency_links.txt
regtricks.egg-info/requires.txt
regtricks.egg-info/top_level.txt
regtricks/transforms/__init__.py
regtricks/transforms/linear.py
regtricks/transforms/nonlinear.py
regtricks/transforms/transform.py