Metadata-Version: 2.1
Name: regtricks
Version: 0.3.3
Summary: Tools for manipulating and applying registrations
Home-page: https://github.com/tomfrankkirk/regtricks
Author: Tom Kirk
Author-email: thomas.kirk@eng.ox.ac.uk
License: BSD-3-clause
Platform: UNKNOWN
